zbzdata/__init__.py
zbzdata/history.py
zbzdata-1.0.0.dist-info/METADATA
zbzdata-1.0.0.dist-info/RECORD
zbzdata-1.0.0.dist-info/WHEEL
zbzdata-1.0.0.dist-info/top_level.txt
zbzdata-1.0.0.dist-info/zip-safe
