Metadata-Version: 2.1
Name: zbzdata
Version: 1.0.0
Summary: project describe
Home-page: http://www.ysteq.com/
Author: ysteq
Author-email: xing.lu@ysteq.com
License: MIT
Platform: UNKNOWN
Classifier: Intended Audience :: Developers
Classifier: Programming Language :: Python
Classifier: Programming Language :: Python :: 3
Classifier: Programming Language :: Python :: 3.6
Classifier: Programming Language :: Python :: 3.7
Classifier: Programming Language :: Python :: 3.8
Classifier: Programming Language :: Python :: 3.9
Classifier: Topic :: Software Development :: Libraries
Requires-Dist: requests (>=2.19.1)
Requires-Dist: lxml (>=3.7.1)
